autoDFT.py
gcutil.py
randomSpheres.py
TurboCoord-0.0.1.dist-info/LICENSE
TurboCoord-0.0.1.dist-info/METADATA
TurboCoord-0.0.1.dist-info/WHEEL
TurboCoord-0.0.1.dist-info/top_level.txt
TurboCoord-0.0.1.dist-info/RECORD
